maplestory/TODO.md
maplestory/__init__.py
maplestory/apis/__init__ copy.py
maplestory/apis/__init__.py
maplestory/apis/character copy.py
maplestory/apis/character.py
maplestory/apis/guild copy 2.py
maplestory/apis/guild copy.py
maplestory/apis/guild.py
maplestory/apis/history copy 2.py
maplestory/apis/history copy.py
maplestory/apis/history.py
maplestory/apis/ranking copy.py
maplestory/apis/ranking.py
maplestory/apis/union copy.py
maplestory/apis/union.py
maplestory/check_update.py
maplestory/client.py
maplestory/config.py
maplestory/enum copy 2.py
maplestory/enum copy.py
maplestory/enums.py
maplestory/error copy.py
maplestory/error.py
maplestory/models/character/__init__.py
maplestory/models/character/ability copy.py
maplestory/models/character/ability.py
maplestory/models/character/android_equip.py
maplestory/models/character/basic copy.py
maplestory/models/character/basic.py
maplestory/models/character/beauty_equip.py
maplestory/models/character/cashitem_equip.py
maplestory/models/character/character.py
maplestory/models/character/dojang copy.py
maplestory/models/character/dojang.py
maplestory/models/character/hexamatrix.py
maplestory/models/character/hexamatrix_stat.py
maplestory/models/character/hyper_stat copy.py
maplestory/models/character/hyper_stat.py
maplestory/models/character/item_equip copy.py
maplestory/models/character/item_equip.py
maplestory/models/character/link_skill.py
maplestory/models/character/pet_equip.py
maplestory/models/character/popularity.py
maplestory/models/character/propensity.py
maplestory/models/character/set_effect copy.py
maplestory/models/character/set_effect.py
maplestory/models/character/skill.py
maplestory/models/character/stat.py
maplestory/models/character/symbol_equip copy.py
maplestory/models/character/symbol_equip.py
maplestory/models/character/vmatrix.py
maplestory/models/class.py
maplestory/models/guild/__init__.py
maplestory/models/guild/basic.py
maplestory/models/guild/guild.py
maplestory/models/history/__init__.py
maplestory_sdk_py-1.0.1.dist-info/LICENSE
maplestory_sdk_py-1.0.1.dist-info/METADATA
maplestory_sdk_py-1.0.1.dist-info/WHEEL
maplestory_sdk_py-1.0.1.dist-info/RECORD
